{
  "tracks": {
    "href": "https://api.spotify.com/v1/search?query=Flowers%2C+year%3D2023&type=track&offset=0&limit=10",
    "items": [
      {
        "album": {
          "album_type": "single",
          "artists": [
            {
              "external_urls": {
                "spotify": "https://open.spotify.com/artist/7IErGg6ZCfFyJJoKGUUBpv"
              },
              "href": "https://api.spotify.com/v1/artists/7IErGg6ZCfFyJJoKGUUBpv",
              "id": "7IErGg6ZCfFyJJoKGUUBpv",
              "name": "accelerate",
              "type": "artist",
              "uri": "spotify:artist:7IErGg6ZCfFyJJoKGUUBpv"
            },
            {
              "external_urls": {
                "spotify": "https://open.spotify.com/artist/2uSVRVjYZ0PlJPdFHnBETu"
              },
              "href": "https://api.spotify.com/v1/artists/2uSVRVjYZ0PlJPdFHnBETu",
              "id": "2uSVRVjYZ0PlJPdFHnBETu",
              "name": "creamy",
              "type": "artist",
              "uri": "spotify:artist:2uSVRVjYZ0PlJPdFHnBETu"
            },
            {
              "external_urls": {
                "spotify": "https://open.spotify.com/artist/2MDj296KJIfgWDNBtHzeFi"
              },
              "href": "https://api.spotify.com/v1/artists/2MDj296KJIfgWDNBtHzeFi",
              "id": "2MDj296KJIfgWDNBtHzeFi",
              "name": "11:11 Music Group",
              "type": "artist",
              "uri": "spotify:artist:2MDj296KJIfgWDNBtHzeFi"
            }
          ],
          "available_markets": [
            "AD",
            "AE",
            "AG",
            "AL",
            "AM",
            "AO",
            "AR",
            "AT",
            "AU",
            "AZ",
            "BA",
            "BB",
            "BD",
            "BE",
            "BF",
            "BG",
            "BH",
            "BI",
            "BJ",
            "BN",
            "BO",
            "BR",
            "BS",
            "BT",
            "BW",
            "BY",
            "BZ",
            "CA",
            "CD",
            "CG",
            "CH",
            "CI",
            "CL",
            "CM",
            "CO",
            "CR",
            "CV",
            "CW",
            "CY",
            "CZ",
            "DE",
            "DJ",
            "DK",
            "DM",
            "DO",
            "DZ",
            "EC",
            "EE",
            "EG",
            "ES",
            "ET",
            "FI",
            "FJ",
            "FM",
            "FR",
            "GA",
            "GB",
            "GD",
            "GE",
            "GH",
            "GM",
            "GN",
            "GQ",
            "GR",
            "GT",
            "GW",
            "GY",
            "HK",
            "HN",
            "HR",
            "HT",
            "HU",
            "ID",
            "IE",
            "IL",
            "IN",
            "IQ",
            "IS",
            "IT",
            "JM",
            "JO",
            "JP",
            "KE",
            "KG",
            "KH",
            "KI",
            "KM",
            "KN",
            "KR",
            "KW",
            "KZ",
            "LA",
            "LB",
            "LC",
            "LI",
            "LK",
            "LR",
            "LS",
            "LT",
            "LU",
            "LV",
            "LY",
            "MA",
            "MC",
            "MD",
            "ME",
            "MG",
            "MH",
            "MK",
            "ML",
            "MN",
            "MO",
            "MR",
            "MT",
            "MU",
            "MV",
            "MW",
            "MX",
            "MY",
            "MZ",
            "NA",
            "NE",
            "NG",
            "NI",
            "NL",
            "NO",
            "NP",
            "NR",
            "NZ",
            "OM",
            "PA",
            "PE",
            "PG",
            "PH",
            "PK",
            "PL",
            "PS",
            "PT",
            "PW",
            "PY",
            "QA",
            "RO",
            "RS",
            "RW",
            "SA",
            "SB",
            "SC",
            "SE",
            "SG",
            "SI",
            "SK",
            "SL",
            "SM",
            "SN",
            "SR",
            "ST",
            "SV",
            "SZ",
            "TD",
            "TG",
            "TH",
            "TJ",
            "TL",
            "TN",
            "TO",
            "TR",
            "TT",
            "TV",
            "TW",
            "TZ",
            "UA",
            "UG",
            "US",
            "UY",
            "UZ",
            "VC",
            "VE",
            "VN",
            "VU",
            "WS",
            "XK",
            "ZA",
            "ZM",
            "ZW"
          ],
          "external_urls": {
            "spotify": "https://open.spotify.com/album/6np72vMyZkvuMWdwKV6nm9"
          },
          "href": "https://api.spotify.com/v1/albums/6np72vMyZkvuMWdwKV6nm9",
          "id": "6np72vMyZkvuMWdwKV6nm9",
          "images": [
            {
              "height": 640,
              "url": "https://i.scdn.co/image/ab67616d0000b2734b091d2a0ab96367a27dea5c",
              "width": 640
            },
            {
              "height": 300,
              "url": "https://i.scdn.co/image/ab67616d00001e024b091d2a0ab96367a27dea5c",
              "width": 300
            },
            {
              "height": 64,
              "url": "https://i.scdn.co/image/ab67616d000048514b091d2a0ab96367a27dea5c",
              "width": 64
            }
          ],
          "name": "flowers (sped up)",
          "release_date": "2023-01-17",
          "release_date_precision": "day",
          "total_tracks": 1,
          "type": "album",
          "uri": "spotify:album:6np72vMyZkvuMWdwKV6nm9"
        },
        "artists": [
          {
            "external_urls": {
              "spotify": "https://open.spotify.com/artist/7IErGg6ZCfFyJJoKGUUBpv"
            },
            "href": "https://api.spotify.com/v1/artists/7IErGg6ZCfFyJJoKGUUBpv",
            "id": "7IErGg6ZCfFyJJoKGUUBpv",
            "name": "accelerate",
            "type": "artist",
            "uri": "spotify:artist:7IErGg6ZCfFyJJoKGUUBpv"
          },
          {
            "external_urls": {
              "spotify": "https://open.spotify.com/artist/2uSVRVjYZ0PlJPdFHnBETu"
            },
            "href": "https://api.spotify.com/v1/artists/2uSVRVjYZ0PlJPdFHnBETu",
            "id": "2uSVRVjYZ0PlJPdFHnBETu",
            "name": "creamy",
            "type": "artist",
            "uri": "spotify:artist:2uSVRVjYZ0PlJPdFHnBETu"
          },
          {
            "external_urls": {
              "spotify": "https://open.spotify.com/artist/2MDj296KJIfgWDNBtHzeFi"
            },
            "href": "https://api.spotify.com/v1/artists/2MDj296KJIfgWDNBtHzeFi",
            "id": "2MDj296KJIfgWDNBtHzeFi",
            "name": "11:11 Music Group",
            "type": "artist",
            "uri": "spotify:artist:2MDj296KJIfgWDNBtHzeFi"
          }
        ],
        "available_markets": [
          "AD",
          "AE",
          "AG",
          "AL",
          "AM",
          "AO",
          "AR",
          "AT",
          "AU",
          "AZ",
          "BA",
          "BB",
          "BD",
          "BE",
          "BF",
          "BG",
          "BH",
          "BI",
          "BJ",
          "BN",
          "BO",
          "BR",
          "BS",
          "BT",
          "BW",
          "BY",
          "BZ",
          "CA",
          "CD",
          "CG",
          "CH",
          "CI",
          "CL",
          "CM",
          "CO",
          "CR",
          "CV",
          "CW",
          "CY",
          "CZ",
          "DE",
          "DJ",
          "DK",
          "DM",
          "DO",
          "DZ",
          "EC",
          "EE",
          "EG",
          "ES",
          "ET",
          "FI",
          "FJ",
          "FM",
          "FR",
          "GA",
          "GB",
          "GD",
          "GE",
          "GH",
          "GM",
          "GN",
          "GQ",
          "GR",
          "GT",
          "GW",
          "GY",
          "HK",
          "HN",
          "HR",
          "HT",
          "HU",
          "ID",
          "IE",
          "IL",
          "IN",
          "IQ",
          "IS",
          "IT",
          "JM",
          "JO",
          "JP",
          "KE",
          "KG",
          "KH",
          "KI",
          "KM",
          "KN",
          "KR",
          "KW",
          "KZ",
          "LA",
          "LB",
          "LC",
          "LI",
          "LK",
          "LR",
          "LS",
          "LT",
          "LU",
          "LV",
          "LY",
          "MA",
          "MC",
          "MD",
          "ME",
          "MG",
          "MH",
          "MK",
          "ML",
          "MN",
          "MO",
          "MR",
          "MT",
          "MU",
          "MV",
          "MW",
          "MX",
          "MY",
          "MZ",
          "NA",
          "NE",
          "NG",
          "NI",
          "NL",
          "NO",
          "NP",
          "NR",
          "NZ",
          "OM",
          "PA",
          "PE",
          "PG",
          "PH",
          "PK",
          "PL",
          "PS",
          "PT",
          "PW",
          "PY",
          "QA",
          "RO",
          "RS",
          "RW",
          "SA",
          "SB",
          "SC",
          "SE",
          "SG",
          "SI",
          "SK",
          "SL",
          "SM",
          "SN",
          "SR",
          "ST",
          "SV",
          "SZ",
          "TD",
          "TG",
          "TH",
          "TJ",
          "TL",
          "TN",
          "TO",
          "TR",
          "TT",
          "TV",
          "TW",
          "TZ",
          "UA",
          "UG",
          "US",
          "UY",
          "UZ",
          "VC",
          "VE",
          "VN",
          "VU",
          "WS",
          "XK",
          "ZA",
          "ZM",
          "ZW"
        ],
        "disc_number": 1,
        "duration_ms": 161567,
        "explicit": false,
        "external_ids": {
          "isrc": "GX89G2355319"
        },
        "external_urls": {
          "spotify": "https://open.spotify.com/track/2oa1uaz9P2dAQxlyOX8nsA"
        },
        "href": "https://api.spotify.com/v1/tracks/2oa1uaz9P2dAQxlyOX8nsA",
        "id": "2oa1uaz9P2dAQxlyOX8nsA",
        "is_local": false,
        "name": "flowers (sped up)",
        "popularity": 37,
        "preview_url": "https://p.scdn.co/mp3-preview/56ce24cd469a432e313c73f73ac2596bf6c84e0b?cid=b5e32fa592ff4292bb18999432fd729a",
        "track_number": 1,
        "type": "track",
        "uri": "spotify:track:2oa1uaz9P2dAQxlyOX8nsA"
      },
      {
        "album": {
          "album_type": "single",
          "artists": [
            {
              "external_urls": {
                "spotify": "https://open.spotify.com/artist/2uSVRVjYZ0PlJPdFHnBETu"
              },
              "href": "https://api.spotify.com/v1/artists/2uSVRVjYZ0PlJPdFHnBETu",
              "id": "2uSVRVjYZ0PlJPdFHnBETu",
              "name": "creamy",
              "type": "artist",
              "uri": "spotify:artist:2uSVRVjYZ0PlJPdFHnBETu"
            },
            {
              "external_urls": {
                "spotify": "https://open.spotify.com/artist/31mtcsgS3CJW5dEPlG83E7"
              },
              "href": "https://api.spotify.com/v1/artists/31mtcsgS3CJW5dEPlG83E7",
              "id": "31mtcsgS3CJW5dEPlG83E7",
              "name": "untrusted",
              "type": "artist",
              "uri": "spotify:artist:31mtcsgS3CJW5dEPlG83E7"
            },
            {
              "external_urls": {
                "spotify": "https://open.spotify.com/artist/2MDj296KJIfgWDNBtHzeFi"
              },
              "href": "https://api.spotify.com/v1/artists/2MDj296KJIfgWDNBtHzeFi",
              "id": "2MDj296KJIfgWDNBtHzeFi",
              "name": "11:11 Music Group",
              "type": "artist",
              "uri": "spotify:artist:2MDj296KJIfgWDNBtHzeFi"
            }
          ],
          "available_markets": [
            "AD",
            "AE",
            "AG",
            "AL",
            "AM",
            "AO",
            "AR",
            "AT",
            "AU",
            "AZ",
            "BA",
            "BB",
            "BD",
            "BE",
            "BF",
            "BG",
            "BH",
            "BI",
            "BJ",
            "BN",
            "BO",
            "BR",
            "BS",
            "BT",
            "BW",
            "BY",
            "BZ",
            "CA",
            "CD",
            "CG",
            "CH",
            "CI",
            "CL",
            "CM",
            "CO",
            "CR",
            "CV",
            "CW",
            "CY",
            "CZ",
            "DE",
            "DJ",
            "DK",
            "DM",
            "DO",
            "DZ",
            "EC",
            "EE",
            "EG",
            "ES",
            "ET",
            "FI",
            "FJ",
            "FM",
            "FR",
            "GA",
            "GB",
            "GD",
            "GE",
            "GH",
            "GM",
            "GN",
            "GQ",
            "GR",
            "GT",
            "GW",
            "GY",
            "HK",
            "HN",
            "HR",
            "HT",
            "HU",
            "ID",
            "IE",
            "IL",
            "IN",
            "IQ",
            "IS",
            "IT",
            "JM",
            "JO",
            "JP",
            "KE",
            "KG",
            "KH",
            "KI",
            "KM",
            "KN",
            "KR",
            "KW",
            "KZ",
            "LA",
            "LB",
            "LC",
            "LI",
            "LK",
            "LR",
            "LS",
            "LT",
            "LU",
            "LV",
            "LY",
            "MA",
            "MC",
            "MD",
            "ME",
            "MG",
            "MH",
            "MK",
            "ML",
            "MN",
            "MO",
            "MR",
            "MT",
            "MU",
            "MV",
            "MW",
            "MX",
            "MY",
            "MZ",
            "NA",
            "NE",
            "NG",
            "NI",
            "NL",
            "NO",
            "NP",
            "NR",
            "NZ",
            "OM",
            "PA",
            "PE",
            "PG",
            "PH",
            "PK",
            "PL",
            "PS",
            "PT",
            "PW",
            "PY",
            "QA",
            "RO",
            "RS",
            "RW",
            "SA",
            "SB",
            "SC",
            "SE",
            "SG",
            "SI",
            "SK",
            "SL",
            "SM",
            "SN",
            "SR",
            "ST",
            "SV",
            "SZ",
            "TD",
            "TG",
            "TH",
            "TJ",
            "TL",
            "TN",
            "TO",
            "TR",
            "TT",
            "TV",
            "TW",
            "TZ",
            "UA",
            "UG",
            "US",
            "UY",
            "UZ",
            "VC",
            "VE",
            "VN",
            "VU",
            "WS",
            "XK",
            "ZA",
            "ZM",
            "ZW"
          ],
          "external_urls": {
            "spotify": "https://open.spotify.com/album/6NcKS9BDypPhlW6QyChl3m"
          },
          "href": "https://api.spotify.com/v1/albums/6NcKS9BDypPhlW6QyChl3m",
          "id": "6NcKS9BDypPhlW6QyChl3m",
          "images": [
            {
              "height": 640,
              "url": "https://i.scdn.co/image/ab67616d0000b2733aa628f841d7e1055d81445f",
              "width": 640
            },
            {
              "height": 300,
              "url": "https://i.scdn.co/image/ab67616d00001e023aa628f841d7e1055d81445f",
              "width": 300
            },
            {
              "height": 64,
              "url": "https://i.scdn.co/image/ab67616d000048513aa628f841d7e1055d81445f",
              "width": 64
            }
          ],
          "name": "flowers (acoustic)",
          "release_date": "2023-01-20",
          "release_date_precision": "day",
          "total_tracks": 1,
          "type": "album",
          "uri": "spotify:album:6NcKS9BDypPhlW6QyChl3m"
        },
        "artists": [
          {
            "external_urls": {
              "spotify": "https://open.spotify.com/artist/2uSVRVjYZ0PlJPdFHnBETu"
            },
            "href": "https://api.spotify.com/v1/artists/2uSVRVjYZ0PlJPdFHnBETu",
            "id": "2uSVRVjYZ0PlJPdFHnBETu",
            "name": "creamy",
            "type": "artist",
            "uri": "spotify:artist:2uSVRVjYZ0PlJPdFHnBETu"
          },
          {
            "external_urls": {
              "spotify": "https://open.spotify.com/artist/31mtcsgS3CJW5dEPlG83E7"
            },
            "href": "https://api.spotify.com/v1/artists/31mtcsgS3CJW5dEPlG83E7",
            "id": "31mtcsgS3CJW5dEPlG83E7",
            "name": "untrusted",
            "type": "artist",
            "uri": "spotify:artist:31mtcsgS3CJW5dEPlG83E7"
          },
          {
            "external_urls": {
              "spotify": "https://open.spotify.com/artist/2MDj296KJIfgWDNBtHzeFi"
            },
            "href": "https://api.spotify.com/v1/artists/2MDj296KJIfgWDNBtHzeFi",
            "id": "2MDj296KJIfgWDNBtHzeFi",
            "name": "11:11 Music Group",
            "type": "artist",
            "uri": "spotify:artist:2MDj296KJIfgWDNBtHzeFi"
          }
        ],
        "available_markets": [
          "AD",
          "AE",
          "AG",
          "AL",
          "AM",
          "AO",
          "AR",
          "AT",
          "AU",
          "AZ",
          "BA",
          "BB",
          "BD",
          "BE",
          "BF",
          "BG",
          "BH",
          "BI",
          "BJ",
          "BN",
          "BO",
          "BR",
          "BS",
          "BT",
          "BW",
          "BY",
          "BZ",
          "CA",
          "CD",
          "CG",
          "CH",
          "CI",
          "CL",
          "CM",
          "CO",
          "CR",
          "CV",
          "CW",
          "CY",
          "CZ",
          "DE",
          "DJ",
          "DK",
          "DM",
          "DO",
          "DZ",
          "EC",
          "EE",
          "EG",
          "ES",
          "ET",
          "FI",
          "FJ",
          "FM",
          "FR",
          "GA",
          "GB",
          "GD",
          "GE",
          "GH",
          "GM",
          "GN",
          "GQ",
          "GR",
          "GT",
          "GW",
          "GY",
          "HK",
          "HN",
          "HR",
          "HT",
          "HU",
          "ID",
          "IE",
          "IL",
          "IN",
          "IQ",
          "IS",
          "IT",
          "JM",
          "JO",
          "JP",
          "KE",
          "KG",
          "KH",
          "KI",
          "KM",
          "KN",
          "KR",
          "KW",
          "KZ",
          "LA",
          "LB",
          "LC",
          "LI",
          "LK",
          "LR",
          "LS",
          "LT",
          "LU",
          "LV",
          "LY",
          "MA",
          "MC",
          "MD",
          "ME",
          "MG",
          "MH",
          "MK",
          "ML",
          "MN",
          "MO",
          "MR",
          "MT",
          "MU",
          "MV",
          "MW",
          "MX",
          "MY",
          "MZ",
          "NA",
          "NE",
          "NG",
          "NI",
          "NL",
          "NO",
          "NP",
          "NR",
          "NZ",
          "OM",
          "PA",
          "PE",
          "PG",
          "PH",
          "PK",
          "PL",
          "PS",
          "PT",
          "PW",
          "PY",
          "QA",
          "RO",
          "RS",
          "RW",
          "SA",
          "SB",
          "SC",
          "SE",
          "SG",
          "SI",
          "SK",
          "SL",
          "SM",
          "SN",
          "SR",
          "ST",
          "SV",
          "SZ",
          "TD",
          "TG",
          "TH",
          "TJ",
          "TL",
          "TN",
          "TO",
          "TR",
          "TT",
          "TV",
          "TW",
          "TZ",
          "UA",
          "UG",
          "US",
          "UY",
          "UZ",
          "VC",
          "VE",
          "VN",
          "VU",
          "WS",
          "XK",
          "ZA",
          "ZM",
          "ZW"
        ],
        "disc_number": 1,
        "duration_ms": 188389,
        "explicit": false,
        "external_ids": {
          "isrc": "GX89G2397473"
        },
        "external_urls": {
          "spotify": "https://open.spotify.com/track/3a3YPQwmugFDYjXAkcSDcG"
        },
        "href": "https://api.spotify.com/v1/tracks/3a3YPQwmugFDYjXAkcSDcG",
        "id": "3a3YPQwmugFDYjXAkcSDcG",
        "is_local": false,
        "name": "flowers (acoustic)",
        "popularity": 27,
        "preview_url": "https://p.scdn.co/mp3-preview/f3c7c6e5eb0a7e0dd668d03cbe834defd80b4783?cid=b5e32fa592ff4292bb18999432fd729a",
        "track_number": 1,
        "type": "track",
        "uri": "spotify:track:3a3YPQwmugFDYjXAkcSDcG"
      },
      {
        "album": {
          "album_type": "single",
          "artists": [
            {
              "external_urls": {
                "spotify": "https://open.spotify.com/artist/4yyfcLKNDz2p5nHRam1dGk"
              },
              "href": "https://api.spotify.com/v1/artists/4yyfcLKNDz2p5nHRam1dGk",
              "id": "4yyfcLKNDz2p5nHRam1dGk",
              "name": "Vallvete",
              "type": "artist",
              "uri": "spotify:artist:4yyfcLKNDz2p5nHRam1dGk"
            },
            {
              "external_urls": {
                "spotify": "https://open.spotify.com/artist/21owPh4qENmViXFjVkvJdd"
              },
              "href": "https://api.spotify.com/v1/artists/21owPh4qENmViXFjVkvJdd",
              "id": "21owPh4qENmViXFjVkvJdd",
              "name": "eyeroze",
              "type": "artist",
              "uri": "spotify:artist:21owPh4qENmViXFjVkvJdd"
            },
            {
              "external_urls": {
                "spotify": "https://open.spotify.com/artist/1VubctelrLfmkt17PiXCHb"
              },
              "href": "https://api.spotify.com/v1/artists/1VubctelrLfmkt17PiXCHb",
              "id": "1VubctelrLfmkt17PiXCHb",
              "name": "Chill Town Records",
              "type": "artist",
              "uri": "spotify:artist:1VubctelrLfmkt17PiXCHb"
            }
          ],
          "available_markets": [
            "AD",
            "AE",
            "AG",
            "AL",
            "AM",
            "AO",
            "AR",
            "AT",
            "AU",
            "AZ",
            "BA",
            "BB",
            "BD",
            "BE",
            "BF",
            "BG",
            "BH",
            "BI",
            "BJ",
            "BN",
            "BO",
            "BR",
            "BS",
            "BT",
            "BW",
            "BY",
            "BZ",
            "CA",
            "CD",
            "CG",
            "CH",
            "CI",
            "CL",
            "CM",
            "CO",
            "CR",
            "CV",
            "CW",
            "CY",
            "CZ",
            "DE",
            "DJ",
            "DK",
            "DM",
            "DO",
            "DZ",
            "EC",
            "EE",
            "EG",
            "ES",
            "ET",
            "FI",
            "FJ",
            "FM",
            "FR",
            "GA",
            "GB",
            "GD",
            "GE",
            "GH",
            "GM",
            "GN",
            "GQ",
            "GR",
            "GT",
            "GW",
            "GY",
            "HK",
            "HN",
            "HR",
            "HT",
            "HU",
            "ID",
            "IE",
            "IL",
            "IN",
            "IQ",
            "IS",
            "IT",
            "JM",
            "JO",
            "JP",
            "KE",
            "KG",
            "KH",
            "KI",
            "KM",
            "KN",
            "KR",
            "KW",
            "KZ",
            "LA",
            "LB",
            "LC",
            "LI",
            "LK",
            "LR",
            "LS",
            "LT",
            "LU",
            "LV",
            "LY",
            "MA",
            "MC",
            "MD",
            "ME",
            "MG",
            "MH",
            "MK",
            "ML",
            "MN",
            "MO",
            "MR",
            "MT",
            "MU",
            "MV",
            "MW",
            "MX",
            "MY",
            "MZ",
            "NA",
            "NE",
            "NG",
            "NI",
            "NL",
            "NO",
            "NP",
            "NR",
            "NZ",
            "OM",
            "PA",
            "PE",
            "PG",
            "PH",
            "PK",
            "PL",
            "PS",
            "PT",
            "PW",
            "PY",
            "QA",
            "RO",
            "RS",
            "RW",
            "SA",
            "SB",
            "SC",
            "SE",
            "SG",
            "SI",
            "SK",
            "SL",
            "SM",
            "SN",
            "SR",
            "ST",
            "SV",
            "SZ",
            "TD",
            "TG",
            "TH",
            "TJ",
            "TL",
            "TN",
            "TO",
            "TR",
            "TT",
            "TV",
            "TW",
            "TZ",
            "UA",
            "UG",
            "US",
            "UY",
            "UZ",
            "VC",
            "VE",
            "VN",
            "VU",
            "WS",
            "XK",
            "ZA",
            "ZM",
            "ZW"
          ],
          "external_urls": {
            "spotify": "https://open.spotify.com/album/7rSxlTRP8HR8RXyWJhegwv"
          },
          "href": "https://api.spotify.com/v1/albums/7rSxlTRP8HR8RXyWJhegwv",
          "id": "7rSxlTRP8HR8RXyWJhegwv",
          "images": [
            {
              "height": 640,
              "url": "https://i.scdn.co/image/ab67616d0000b2737cc28fd0268349dbdb870a91",
              "width": 640
            },
            {
              "height": 300,
              "url": "https://i.scdn.co/image/ab67616d00001e027cc28fd0268349dbdb870a91",
              "width": 300
            },
            {
              "height": 64,
              "url": "https://i.scdn.co/image/ab67616d000048517cc28fd0268349dbdb870a91",
              "width": 64
            }
          ],
          "name": "flowers - slowed + reverb",
          "release_date": "2023-01-25",
          "release_date_precision": "day",
          "total_tracks": 1,
          "type": "album",
          "uri": "spotify:album:7rSxlTRP8HR8RXyWJhegwv"
        },
        "artists": [
          {
            "external_urls": {
              "spotify": "https://open.spotify.com/artist/4yyfcLKNDz2p5nHRam1dGk"
            },
            "href": "https://api.spotify.com/v1/artists/4yyfcLKNDz2p5nHRam1dGk",
            "id": "4yyfcLKNDz2p5nHRam1dGk",
            "name": "Vallvete",
            "type": "artist",
            "uri": "spotify:artist:4yyfcLKNDz2p5nHRam1dGk"
          },
          {
            "external_urls": {
              "spotify": "https://open.spotify.com/artist/21owPh4qENmViXFjVkvJdd"
            },
            "href": "https://api.spotify.com/v1/artists/21owPh4qENmViXFjVkvJdd",
            "id": "21owPh4qENmViXFjVkvJdd",
            "name": "eyeroze",
            "type": "artist",
            "uri": "spotify:artist:21owPh4qENmViXFjVkvJdd"
          },
          {
            "external_urls": {
              "spotify": "https://open.spotify.com/artist/1VubctelrLfmkt17PiXCHb"
            },
            "href": "https://api.spotify.com/v1/artists/1VubctelrLfmkt17PiXCHb",
            "id": "1VubctelrLfmkt17PiXCHb",
            "name": "Chill Town Records",
            "type": "artist",
            "uri": "spotify:artist:1VubctelrLfmkt17PiXCHb"
          }
        ],
        "available_markets": [
          "AD",
          "AE",
          "AG",
          "AL",
          "AM",
          "AO",
          "AR",
          "AT",
          "AU",
          "AZ",
          "BA",
          "BB",
          "BD",
          "BE",
          "BF",
          "BG",
          "BH",
          "BI",
          "BJ",
          "BN",
          "BO",
          "BR",
          "BS",
          "BT",
          "BW",
          "BY",
          "BZ",
          "CA",
          "CD",
          "CG",
          "CH",
          "CI",
          "CL",
          "CM",
          "CO",
          "CR",
          "CV",
          "CW",
          "CY",
          "CZ",
          "DE",
          "DJ",
          "DK",
          "DM",
          "DO",
          "DZ",
          "EC",
          "EE",
          "EG",
          "ES",
          "ET",
          "FI",
          "FJ",
          "FM",
          "FR",
          "GA",
          "GB",
          "GD",
          "GE",
          "GH",
          "GM",
          "GN",
          "GQ",
          "GR",
          "GT",
          "GW",
          "GY",
          "HK",
          "HN",
          "HR",
          "HT",
          "HU",
          "ID",
          "IE",
          "IL",
          "IN",
          "IQ",
          "IS",
          "IT",
          "JM",
          "JO",
          "JP",
          "KE",
          "KG",
          "KH",
          "KI",
          "KM",
          "KN",
          "KR",
          "KW",
          "KZ",
          "LA",
          "LB",
          "LC",
          "LI",
          "LK",
          "LR",
          "LS",
          "LT",
          "LU",
          "LV",
          "LY",
          "MA",
          "MC",
          "MD",
          "ME",
          "MG",
          "MH",
          "MK",
          "ML",
          "MN",
          "MO",
          "MR",
          "MT",
          "MU",
          "MV",
          "MW",
          "MX",
          "MY",
          "MZ",
          "NA",
          "NE",
          "NG",
          "NI",
          "NL",
          "NO",
          "NP",
          "NR",
          "NZ",
          "OM",
          "PA",
          "PE",
          "PG",
          "PH",
          "PK",
          "PL",
          "PS",
          "PT",
          "PW",
          "PY",
          "QA",
          "RO",
          "RS",
          "RW",
          "SA",
          "SB",
          "SC",
          "SE",
          "SG",
          "SI",
          "SK",
          "SL",
          "SM",
          "SN",
          "SR",
          "ST",
          "SV",
          "SZ",
          "TD",
          "TG",
          "TH",
          "TJ",
          "TL",
          "TN",
          "TO",
          "TR",
          "TT",
          "TV",
          "TW",
          "TZ",
          "UA",
          "UG",
          "US",
          "UY",
          "UZ",
          "VC",
          "VE",
          "VN",
          "VU",
          "WS",
          "XK",
          "ZA",
          "ZM",
          "ZW"
        ],
        "disc_number": 1,
        "duration_ms": 232592,
        "explicit": false,
        "external_ids": {
          "isrc": "GX89G2311324"
        },
        "external_urls": {
          "spotify": "https://open.spotify.com/track/2F5OTjxqrRPhSMWChhcl1A"
        },
        "href": "https://api.spotify.com/v1/tracks/2F5OTjxqrRPhSMWChhcl1A",
        "id": "2F5OTjxqrRPhSMWChhcl1A",
        "is_local": false,
        "name": "flowers - slowed + reverb",
        "popularity": 18,
        "preview_url": "https://p.scdn.co/mp3-preview/a4a95c398f9fc2d3486ea163cc8fc96f822bcabd?cid=b5e32fa592ff4292bb18999432fd729a",
        "track_number": 1,
        "type": "track",
        "uri": "spotify:track:2F5OTjxqrRPhSMWChhcl1A"
      },
      {
        "album": {
          "album_type": "compilation",
          "artists": [
            {
              "external_urls": {
                "spotify": "https://open.spotify.com/artist/0LyfQWJT6nXafLPZqxe9Of"
              },
              "href": "https://api.spotify.com/v1/artists/0LyfQWJT6nXafLPZqxe9Of",
              "id": "0LyfQWJT6nXafLPZqxe9Of",
              "name": "Various Artists",
              "type": "artist",
              "uri": "spotify:artist:0LyfQWJT6nXafLPZqxe9Of"
            }
          ],
          "available_markets": [
            "AE",
            "AL",
            "AR",
            "AT",
            "AU",
            "BA",
            "BE",
            "BG",
            "BH",
            "BO",
            "BR",
            "CA",
            "CH",
            "CI",
            "CL",
            "CM",
            "CO",
            "CR",
            "CW",
            "CY",
            "CZ",
            "DE",
            "DK",
            "DO",
            "DZ",
            "EC",
            "EE",
            "EG",
            "ES",
            "FI",
            "FR",
            "GB",
            "GH",
            "GR",
            "GT",
            "HK",
            "HN",
            "HR",
            "HU",
            "ID",
            "IE",
            "IL",
            "IN",
            "IS",
            "IT",
            "JP",
            "KE",
            "KH",
            "KR",
            "KW",
            "LB",
            "LK",
            "LT",
            "LU",
            "LV",
            "MA",
            "ME",
            "MK",
            "MT",
            "MX",
            "MY",
            "NG",
            "NI",
            "NL",
            "NO",
            "NZ",
            "OM",
            "PA",
            "PE",
            "PH",
            "PL",
            "PT",
            "PY",
            "QA",
            "RO",
            "RS",
            "SA",
            "SE",
            "SG",
            "SI",
            "SK",
            "SN",
            "SV",
            "TH",
            "TN",
            "TR",
            "TT",
            "TW",
            "UA",
            "US",
            "UY",
            "VE",
            "VN",
            "XK",
            "ZA"
          ],
          "external_urls": {
            "spotify": "https://open.spotify.com/album/4j8WQT2cQ86SYtAGgicmBW"
          },
          "href": "https://api.spotify.com/v1/albums/4j8WQT2cQ86SYtAGgicmBW",
          "id": "4j8WQT2cQ86SYtAGgicmBW",
          "images": [
            {
              "height": 640,
              "url": "https://i.scdn.co/image/ab67616d0000b273c377dcae4994b338de60eb6b",
              "width": 640
            },
            {
              "height": 300,
              "url": "https://i.scdn.co/image/ab67616d00001e02c377dcae4994b338de60eb6b",
              "width": 300
            },
            {
              "height": 64,
              "url": "https://i.scdn.co/image/ab67616d00004851c377dcae4994b338de60eb6b",
              "width": 64
            }
          ],
          "name": "New Years Party 2023",
          "release_date": "2022-12-01",
          "release_date_precision": "day",
          "total_tracks": 53,
          "type": "album",
          "uri": "spotify:album:4j8WQT2cQ86SYtAGgicmBW"
        },
        "artists": [
          {
            "external_urls": {
              "spotify": "https://open.spotify.com/artist/5TvdGhdmRObqOkU6eGfXb5"
            },
            "href": "https://api.spotify.com/v1/artists/5TvdGhdmRObqOkU6eGfXb5",
            "id": "5TvdGhdmRObqOkU6eGfXb5",
            "name": "Preston Pablo",
            "type": "artist",
            "uri": "spotify:artist:5TvdGhdmRObqOkU6eGfXb5"
          },
          {
            "external_urls": {
              "spotify": "https://open.spotify.com/artist/2uFC1dAj5b0YU7vulKNZ0p"
            },
            "href": "https://api.spotify.com/v1/artists/2uFC1dAj5b0YU7vulKNZ0p",
            "id": "2uFC1dAj5b0YU7vulKNZ0p",
            "name": "Banx & Ranx",
            "type": "artist",
            "uri": "spotify:artist:2uFC1dAj5b0YU7vulKNZ0p"
          }
        ],
        "available_markets": [
          "AE",
          "AL",
          "AR",
          "AT",
          "AU",
          "BA",
          "BE",
          "BG",
          "BH",
          "BO",
          "BR",
          "CA",
          "CH",
          "CI",
          "CL",
          "CM",
          "CO",
          "CR",
          "CW",
          "CY",
          "CZ",
          "DE",
          "DK",
          "DO",
          "DZ",
          "EC",
          "EE",
          "EG",
          "ES",
          "FI",
          "FR",
          "GB",
          "GH",
          "GR",
          "GT",
          "HK",
          "HN",
          "HR",
          "HU",
          "ID",
          "IE",
          "IL",
          "IN",
          "IS",
          "IT",
          "JP",
          "KE",
          "KH",
          "KR",
          "KW",
          "LB",
          "LK",
          "LT",
          "LU",
          "LV",
          "MA",
          "ME",
          "MK",
          "MT",
          "MX",
          "MY",
          "NG",
          "NI",
          "NL",
          "NO",
          "NZ",
          "OM",
          "PA",
          "PE",
          "PH",
          "PL",
          "PT",
          "PY",
          "QA",
          "RO",
          "RS",
          "SA",
          "SE",
          "SG",
          "SI",
          "SK",
          "SN",
          "SV",
          "TH",
          "TN",
          "TR",
          "TT",
          "TW",
          "UA",
          "US",
          "UY",
          "VE",
          "VN",
          "XK",
          "ZA"
        ],
        "disc_number": 1,
        "duration_ms": 168126,
        "explicit": false,
        "external_ids": {
          "isrc": "CAUM72200107"
        },
        "external_urls": {
          "spotify": "https://open.spotify.com/track/2RLkGtLAMtPITmSeiizfS6"
        },
        "href": "https://api.spotify.com/v1/tracks/2RLkGtLAMtPITmSeiizfS6",
        "id": "2RLkGtLAMtPITmSeiizfS6",
        "is_local": false,
        "name": "Flowers Need Rain",
        "popularity": 0,
        "preview_url": "https://p.scdn.co/mp3-preview/85b3f070b2fd3b09ce62bc885996896eb2062bb2?cid=b5e32fa592ff4292bb18999432fd729a",
        "track_number": 24,
        "type": "track",
        "uri": "spotify:track:2RLkGtLAMtPITmSeiizfS6"
      },
      {
        "album": {
          "album_type": "single",
          "artists": [
            {
              "external_urls": {
                "spotify": "https://open.spotify.com/artist/5qA4H8JJ6VCAN41tE9o3KW"
              },
              "href": "https://api.spotify.com/v1/artists/5qA4H8JJ6VCAN41tE9o3KW",
              "id": "5qA4H8JJ6VCAN41tE9o3KW",
              "name": "Feathersmith",
              "type": "artist",
              "uri": "spotify:artist:5qA4H8JJ6VCAN41tE9o3KW"
            }
          ],
          "available_markets": [
            "AD",
            "AE",
            "AG",
            "AL",
            "AM",
            "AO",
            "AR",
            "AT",
            "AU",
            "AZ",
            "BA",
            "BB",
            "BD",
            "BE",
            "BF",
            "BG",
            "BH",
            "BI",
            "BJ",
            "BN",
            "BO",
            "BR",
            "BS",
            "BT",
            "BW",
            "BY",
            "BZ",
            "CA",
            "CD",
            "CG",
            "CH",
            "CI",
            "CL",
            "CM",
            "CO",
            "CR",
            "CV",
            "CW",
            "CY",
            "CZ",
            "DE",
            "DJ",
            "DK",
            "DM",
            "DO",
            "DZ",
            "EC",
            "EE",
            "EG",
            "ES",
            "ET",
            "FI",
            "FJ",
            "FM",
            "FR",
            "GA",
            "GB",
            "GD",
            "GE",
            "GH",
            "GM",
            "GN",
            "GQ",
            "GR",
            "GT",
            "GW",
            "GY",
            "HK",
            "HN",
            "HR",
            "HT",
            "HU",
            "ID",
            "IE",
            "IL",
            "IN",
            "IQ",
            "IS",
            "IT",
            "JM",
            "JO",
            "JP",
            "KE",
            "KG",
            "KH",
            "KI",
            "KM",
            "KN",
            "KR",
            "KW",
            "KZ",
            "LA",
            "LB",
            "LC",
            "LI",
            "LK",
            "LR",
            "LS",
            "LT",
            "LU",
            "LV",
            "LY",
            "MA",
            "MC",
            "MD",
            "ME",
            "MG",
            "MH",
            "MK",
            "ML",
            "MN",
            "MO",
            "MR",
            "MT",
            "MU",
            "MV",
            "MW",
            "MX",
            "MY",
            "MZ",
            "NA",
            "NE",
            "NG",
            "NI",
            "NL",
            "NO",
            "NP",
            "NR",
            "NZ",
            "OM",
            "PA",
            "PE",
            "PG",
            "PH",
            "PK",
            "PL",
            "PS",
            "PT",
            "PW",
            "PY",
            "QA",
            "RO",
            "RS",
            "RW",
            "SA",
            "SB",
            "SC",
            "SE",
            "SG",
            "SI",
            "SK",
            "SL",
            "SM",
            "SN",
            "SR",
            "ST",
            "SV",
            "SZ",
            "TD",
            "TG",
            "TH",
            "TJ",
            "TL",
            "TN",
            "TO",
            "TR",
            "TT",
            "TV",
            "TW",
            "TZ",
            "UA",
            "UG",
            "US",
            "UY",
            "UZ",
            "VC",
            "VE",
            "VN",
            "VU",
            "WS",
            "XK",
            "ZA",
            "ZM",
            "ZW"
          ],
          "external_urls": {
            "spotify": "https://open.spotify.com/album/0kPG984DzfnVH3i9IBkGJb"
          },
          "href": "https://api.spotify.com/v1/albums/0kPG984DzfnVH3i9IBkGJb",
          "id": "0kPG984DzfnVH3i9IBkGJb",
          "images": [
            {
              "height": 640,
              "url": "https://i.scdn.co/image/ab67616d0000b27386fead941ec58208f3e7ef15",
              "width": 640
            },
            {
              "height": 300,
              "url": "https://i.scdn.co/image/ab67616d00001e0286fead941ec58208f3e7ef15",
              "width": 300
            },
            {
              "height": 64,
              "url": "https://i.scdn.co/image/ab67616d0000485186fead941ec58208f3e7ef15",
              "width": 64
            }
          ],
          "name": "Flower's Song",
          "release_date": "2019-12-07",
          "release_date_precision": "day",
          "total_tracks": 1,
          "type": "album",
          "uri": "spotify:album:0kPG984DzfnVH3i9IBkGJb"
        },
        "artists": [
          {
            "external_urls": {
              "spotify": "https://open.spotify.com/artist/5qA4H8JJ6VCAN41tE9o3KW"
            },
            "href": "https://api.spotify.com/v1/artists/5qA4H8JJ6VCAN41tE9o3KW",
            "id": "5qA4H8JJ6VCAN41tE9o3KW",
            "name": "Feathersmith",
            "type": "artist",
            "uri": "spotify:artist:5qA4H8JJ6VCAN41tE9o3KW"
          }
        ],
        "available_markets": [
          "AD",
          "AE",
          "AG",
          "AL",
          "AM",
          "AO",
          "AR",
          "AT",
          "AU",
          "AZ",
          "BA",
          "BB",
          "BD",
          "BE",
          "BF",
          "BG",
          "BH",
          "BI",
          "BJ",
          "BN",
          "BO",
          "BR",
          "BS",
          "BT",
          "BW",
          "BY",
          "BZ",
          "CA",
          "CD",
          "CG",
          "CH",
          "CI",
          "CL",
          "CM",
          "CO",
          "CR",
          "CV",
          "CW",
          "CY",
          "CZ",
          "DE",
          "DJ",
          "DK",
          "DM",
          "DO",
          "DZ",
          "EC",
          "EE",
          "EG",
          "ES",
          "ET",
          "FI",
          "FJ",
          "FM",
          "FR",
          "GA",
          "GB",
          "GD",
          "GE",
          "GH",
          "GM",
          "GN",
          "GQ",
          "GR",
          "GT",
          "GW",
          "GY",
          "HK",
          "HN",
          "HR",
          "HT",
          "HU",
          "ID",
          "IE",
          "IL",
          "IN",
          "IQ",
          "IS",
          "IT",
          "JM",
          "JO",
          "JP",
          "KE",
          "KG",
          "KH",
          "KI",
          "KM",
          "KN",
          "KR",
          "KW",
          "KZ",
          "LA",
          "LB",
          "LC",
          "LI",
          "LK",
          "LR",
          "LS",
          "LT",
          "LU",
          "LV",
          "LY",
          "MA",
          "MC",
          "MD",
          "ME",
          "MG",
          "MH",
          "MK",
          "ML",
          "MN",
          "MO",
          "MR",
          "MT",
          "MU",
          "MV",
          "MW",
          "MX",
          "MY",
          "MZ",
          "NA",
          "NE",
          "NG",
          "NI",
          "NL",
          "NO",
          "NP",
          "NR",
          "NZ",
          "OM",
          "PA",
          "PE",
          "PG",
          "PH",
          "PK",
          "PL",
          "PS",
          "PT",
          "PW",
          "PY",
          "QA",
          "RO",
          "RS",
          "RW",
          "SA",
          "SB",
          "SC",
          "SE",
          "SG",
          "SI",
          "SK",
          "SL",
          "SM",
          "SN",
          "SR",
          "ST",
          "SV",
          "SZ",
          "TD",
          "TG",
          "TH",
          "TJ",
          "TL",
          "TN",
          "TO",
          "TR",
          "TT",
          "TV",
          "TW",
          "TZ",
          "UA",
          "UG",
          "US",
          "UY",
          "UZ",
          "VC",
          "VE",
          "VN",
          "VU",
          "WS",
          "XK",
          "ZA",
          "ZM",
          "ZW"
        ],
        "disc_number": 1,
        "duration_ms": 135968,
        "explicit": false,
        "external_ids": {
          "isrc": "GBSMU7287819"
        },
        "external_urls": {
          "spotify": "https://open.spotify.com/track/7eJP7yUp3xVj3vtpqwaUrz"
        },
        "href": "https://api.spotify.com/v1/tracks/7eJP7yUp3xVj3vtpqwaUrz",
        "id": "7eJP7yUp3xVj3vtpqwaUrz",
        "is_local": false,
        "name": "Flower's Song",
        "popularity": 44,
        "preview_url": "https://p.scdn.co/mp3-preview/75aa4aef2c2edb54c96758fa0709c7131fec9baa?cid=b5e32fa592ff4292bb18999432fd729a",
        "track_number": 1,
        "type": "track",
        "uri": "spotify:track:7eJP7yUp3xVj3vtpqwaUrz"
      },
      {
        "album": {
          "album_type": "single",
          "artists": [
            {
              "external_urls": {
                "spotify": "https://open.spotify.com/artist/5XX4TUGKzgEN86IXpNLmgB"
              },
              "href": "https://api.spotify.com/v1/artists/5XX4TUGKzgEN86IXpNLmgB",
              "id": "5XX4TUGKzgEN86IXpNLmgB",
              "name": "Keyli Queen",
              "type": "artist",
              "uri": "spotify:artist:5XX4TUGKzgEN86IXpNLmgB"
            }
          ],
          "available_markets": [
            "AD",
            "AE",
            "AG",
            "AL",
            "AM",
            "AO",
            "AR",
            "AT",
            "AU",
            "AZ",
            "BA",
            "BB",
            "BD",
            "BE",
            "BF",
            "BG",
            "BH",
            "BI",
            "BJ",
            "BN",
            "BO",
            "BR",
            "BS",
            "BT",
            "BW",
            "BY",
            "BZ",
            "CA",
            "CD",
            "CG",
            "CH",
            "CI",
            "CL",
            "CM",
            "CO",
            "CR",
            "CV",
            "CW",
            "CY",
            "CZ",
            "DE",
            "DJ",
            "DK",
            "DM",
            "DO",
            "DZ",
            "EC",
            "EE",
            "EG",
            "ES",
            "ET",
            "FI",
            "FJ",
            "FM",
            "FR",
            "GA",
            "GB",
            "GD",
            "GE",
            "GH",
            "GM",
            "GN",
            "GQ",
            "GR",
            "GT",
            "GW",
            "GY",
            "HK",
            "HN",
            "HR",
            "HT",
            "HU",
            "ID",
            "IE",
            "IL",
            "IN",
            "IQ",
            "IS",
            "IT",
            "JM",
            "JO",
            "JP",
            "KE",
            "KG",
            "KH",
            "KI",
            "KM",
            "KN",
            "KR",
            "KW",
            "KZ",
            "LA",
            "LB",
            "LC",
            "LI",
            "LK",
            "LR",
            "LS",
            "LT",
            "LU",
            "LV",
            "LY",
            "MA",
            "MC",
            "MD",
            "ME",
            "MG",
            "MH",
            "MK",
            "ML",
            "MN",
            "MO",
            "MR",
            "MT",
            "MU",
            "MV",
            "MW",
            "MX",
            "MY",
            "MZ",
            "NA",
            "NE",
            "NG",
            "NI",
            "NL",
            "NO",
            "NP",
            "NR",
            "NZ",
            "OM",
            "PA",
            "PE",
            "PG",
            "PH",
            "PK",
            "PL",
            "PS",
            "PT",
            "PW",
            "PY",
            "QA",
            "RO",
            "RS",
            "RW",
            "SA",
            "SB",
            "SC",
            "SE",
            "SG",
            "SI",
            "SK",
            "SL",
            "SM",
            "SN",
            "SR",
            "ST",
            "SV",
            "SZ",
            "TD",
            "TG",
            "TH",
            "TJ",
            "TL",
            "TN",
            "TO",
            "TR",
            "TT",
            "TV",
            "TW",
            "TZ",
            "UA",
            "UG",
            "US",
            "UY",
            "UZ",
            "VC",
            "VE",
            "VN",
            "VU",
            "WS",
            "XK",
            "ZA",
            "ZM",
            "ZW"
          ],
          "external_urls": {
            "spotify": "https://open.spotify.com/album/4BeBlSIglWYUVIc7HGLuRC"
          },
          "href": "https://api.spotify.com/v1/albums/4BeBlSIglWYUVIc7HGLuRC",
          "id": "4BeBlSIglWYUVIc7HGLuRC",
          "images": [
            {
              "height": 640,
              "url": "https://i.scdn.co/image/ab67616d0000b27344d46d2600f99755e7bd6340",
              "width": 640
            },
            {
              "height": 300,
              "url": "https://i.scdn.co/image/ab67616d00001e0244d46d2600f99755e7bd6340",
              "width": 300
            },
            {
              "height": 64,
              "url": "https://i.scdn.co/image/ab67616d0000485144d46d2600f99755e7bd6340",
              "width": 64
            }
          ],
          "name": "Flowers en espa\u00f1ol",
          "release_date": "2023-01-29",
          "release_date_precision": "day",
          "total_tracks": 1,
          "type": "album",
          "uri": "spotify:album:4BeBlSIglWYUVIc7HGLuRC"
        },
        "artists": [
          {
            "external_urls": {
              "spotify": "https://open.spotify.com/artist/5XX4TUGKzgEN86IXpNLmgB"
            },
            "href": "https://api.spotify.com/v1/artists/5XX4TUGKzgEN86IXpNLmgB",
            "id": "5XX4TUGKzgEN86IXpNLmgB",
            "name": "Keyli Queen",
            "type": "artist",
            "uri": "spotify:artist:5XX4TUGKzgEN86IXpNLmgB"
          }
        ],
        "available_markets": [
          "AD",
          "AE",
          "AG",
          "AL",
          "AM",
          "AO",
          "AR",
          "AT",
          "AU",
          "AZ",
          "BA",
          "BB",
          "BD",
          "BE",
          "BF",
          "BG",
          "BH",
          "BI",
          "BJ",
          "BN",
          "BO",
          "BR",
          "BS",
          "BT",
          "BW",
          "BY",
          "BZ",
          "CA",
          "CD",
          "CG",
          "CH",
          "CI",
          "CL",
          "CM",
          "CO",
          "CR",
          "CV",
          "CW",
          "CY",
          "CZ",
          "DE",
          "DJ",
          "DK",
          "DM",
          "DO",
          "DZ",
          "EC",
          "EE",
          "EG",
          "ES",
          "ET",
          "FI",
          "FJ",
          "FM",
          "FR",
          "GA",
          "GB",
          "GD",
          "GE",
          "GH",
          "GM",
          "GN",
          "GQ",
          "GR",
          "GT",
          "GW",
          "GY",
          "HK",
          "HN",
          "HR",
          "HT",
          "HU",
          "ID",
          "IE",
          "IL",
          "IN",
          "IQ",
          "IS",
          "IT",
          "JM",
          "JO",
          "JP",
          "KE",
          "KG",
          "KH",
          "KI",
          "KM",
          "KN",
          "KR",
          "KW",
          "KZ",
          "LA",
          "LB",
          "LC",
          "LI",
          "LK",
          "LR",
          "LS",
          "LT",
          "LU",
          "LV",
          "LY",
          "MA",
          "MC",
          "MD",
          "ME",
          "MG",
          "MH",
          "MK",
          "ML",
          "MN",
          "MO",
          "MR",
          "MT",
          "MU",
          "MV",
          "MW",
          "MX",
          "MY",
          "MZ",
          "NA",
          "NE",
          "NG",
          "NI",
          "NL",
          "NO",
          "NP",
          "NR",
          "NZ",
          "OM",
          "PA",
          "PE",
          "PG",
          "PH",
          "PK",
          "PL",
          "PS",
          "PT",
          "PW",
          "PY",
          "QA",
          "RO",
          "RS",
          "RW",
          "SA",
          "SB",
          "SC",
          "SE",
          "SG",
          "SI",
          "SK",
          "SL",
          "SM",
          "SN",
          "SR",
          "ST",
          "SV",
          "SZ",
          "TD",
          "TG",
          "TH",
          "TJ",
          "TL",
          "TN",
          "TO",
          "TR",
          "TT",
          "TV",
          "TW",
          "TZ",
          "UA",
          "UG",
          "US",
          "UY",
          "UZ",
          "VC",
          "VE",
          "VN",
          "VU",
          "WS",
          "XK",
          "ZA",
          "ZM",
          "ZW"
        ],
        "disc_number": 1,
        "duration_ms": 193541,
        "explicit": false,
        "external_ids": {
          "isrc": "QZFZ62367075"
        },
        "external_urls": {
          "spotify": "https://open.spotify.com/track/3JaKF8vNDXrzvvhvpnLpyC"
        },
        "href": "https://api.spotify.com/v1/tracks/3JaKF8vNDXrzvvhvpnLpyC",
        "id": "3JaKF8vNDXrzvvhvpnLpyC",
        "is_local": false,
        "name": "Flowers en espa\u00f1ol",
        "popularity": 21,
        "preview_url": "https://p.scdn.co/mp3-preview/2ee619702e4b3863861408a2443f119a70e13517?cid=b5e32fa592ff4292bb18999432fd729a",
        "track_number": 1,
        "type": "track",
        "uri": "spotify:track:3JaKF8vNDXrzvvhvpnLpyC"
      },
      {
        "album": {
          "album_type": "album",
          "artists": [
            {
              "external_urls": {
                "spotify": "https://open.spotify.com/artist/1EJzWKVDeysgbyuZGfEFde"
              },
              "href": "https://api.spotify.com/v1/artists/1EJzWKVDeysgbyuZGfEFde",
              "id": "1EJzWKVDeysgbyuZGfEFde",
              "name": "The Deli",
              "type": "artist",
              "uri": "spotify:artist:1EJzWKVDeysgbyuZGfEFde"
            }
          ],
          "available_markets": [
            "AD",
            "AE",
            "AG",
            "AL",
            "AM",
            "AO",
            "AR",
            "AT",
            "AU",
            "AZ",
            "BA",
            "BB",
            "BD",
            "BE",
            "BF",
            "BG",
            "BH",
            "BI",
            "BJ",
            "BN",
            "BO",
            "BR",
            "BS",
            "BT",
            "BW",
            "BY",
            "BZ",
            "CA",
            "CD",
            "CG",
            "CH",
            "CI",
            "CL",
            "CM",
            "CO",
            "CR",
            "CV",
            "CW",
            "CY",
            "CZ",
            "DE",
            "DJ",
            "DK",
            "DM",
            "DO",
            "DZ",
            "EC",
            "EE",
            "EG",
            "ES",
            "ET",
            "FI",
            "FJ",
            "FM",
            "FR",
            "GA",
            "GB",
            "GD",
            "GE",
            "GH",
            "GM",
            "GN",
            "GQ",
            "GR",
            "GT",
            "GW",
            "GY",
            "HK",
            "HN",
            "HR",
            "HT",
            "HU",
            "ID",
            "IE",
            "IL",
            "IN",
            "IQ",
            "IS",
            "IT",
            "JM",
            "JO",
            "JP",
            "KE",
            "KG",
            "KH",
            "KI",
            "KM",
            "KN",
            "KR",
            "KW",
            "KZ",
            "LA",
            "LB",
            "LC",
            "LI",
            "LK",
            "LR",
            "LS",
            "LT",
            "LU",
            "LV",
            "LY",
            "MA",
            "MC",
            "MD",
            "ME",
            "MG",
            "MH",
            "MK",
            "ML",
            "MN",
            "MO",
            "MR",
            "MT",
            "MU",
            "MV",
            "MW",
            "MX",
            "MY",
            "MZ",
            "NA",
            "NE",
            "NG",
            "NI",
            "NL",
            "NO",
            "NP",
            "NR",
            "NZ",
            "OM",
            "PA",
            "PE",
            "PG",
            "PH",
            "PK",
            "PL",
            "PS",
            "PT",
            "PW",
            "PY",
            "QA",
            "RO",
            "RS",
            "RW",
            "SA",
            "SB",
            "SC",
            "SE",
            "SG",
            "SI",
            "SK",
            "SL",
            "SM",
            "SN",
            "SR",
            "ST",
            "SV",
            "SZ",
            "TD",
            "TG",
            "TH",
            "TJ",
            "TL",
            "TN",
            "TO",
            "TR",
            "TT",
            "TV",
            "TW",
            "TZ",
            "UA",
            "UG",
            "US",
            "UY",
            "UZ",
            "VC",
            "VE",
            "VN",
            "VU",
            "WS",
            "XK",
            "ZA",
            "ZM",
            "ZW"
          ],
          "external_urls": {
            "spotify": "https://open.spotify.com/album/1DewSgsGUFhSPACbWtmZGa"
          },
          "href": "https://api.spotify.com/v1/albums/1DewSgsGUFhSPACbWtmZGa",
          "id": "1DewSgsGUFhSPACbWtmZGa",
          "images": [
            {
              "height": 640,
              "url": "https://i.scdn.co/image/ab67616d0000b273247f9a30e283798d925b71b1",
              "width": 640
            },
            {
              "height": 300,
              "url": "https://i.scdn.co/image/ab67616d00001e02247f9a30e283798d925b71b1",
              "width": 300
            },
            {
              "height": 64,
              "url": "https://i.scdn.co/image/ab67616d00004851247f9a30e283798d925b71b1",
              "width": 64
            }
          ],
          "name": "Vibes 3",
          "release_date": "2016-02-26",
          "release_date_precision": "day",
          "total_tracks": 18,
          "type": "album",
          "uri": "spotify:album:1DewSgsGUFhSPACbWtmZGa"
        },
        "artists": [
          {
            "external_urls": {
              "spotify": "https://open.spotify.com/artist/1EJzWKVDeysgbyuZGfEFde"
            },
            "href": "https://api.spotify.com/v1/artists/1EJzWKVDeysgbyuZGfEFde",
            "id": "1EJzWKVDeysgbyuZGfEFde",
            "name": "The Deli",
            "type": "artist",
            "uri": "spotify:artist:1EJzWKVDeysgbyuZGfEFde"
          }
        ],
        "available_markets": [
          "AD",
          "AE",
          "AG",
          "AL",
          "AM",
          "AO",
          "AR",
          "AT",
          "AU",
          "AZ",
          "BA",
          "BB",
          "BD",
          "BE",
          "BF",
          "BG",
          "BH",
          "BI",
          "BJ",
          "BN",
          "BO",
          "BR",
          "BS",
          "BT",
          "BW",
          "BY",
          "BZ",
          "CA",
          "CD",
          "CG",
          "CH",
          "CI",
          "CL",
          "CM",
          "CO",
          "CR",
          "CV",
          "CW",
          "CY",
          "CZ",
          "DE",
          "DJ",
          "DK",
          "DM",
          "DO",
          "DZ",
          "EC",
          "EE",
          "EG",
          "ES",
          "ET",
          "FI",
          "FJ",
          "FM",
          "FR",
          "GA",
          "GB",
          "GD",
          "GE",
          "GH",
          "GM",
          "GN",
          "GQ",
          "GR",
          "GT",
          "GW",
          "GY",
          "HK",
          "HN",
          "HR",
          "HT",
          "HU",
          "ID",
          "IE",
          "IL",
          "IN",
          "IQ",
          "IS",
          "IT",
          "JM",
          "JO",
          "JP",
          "KE",
          "KG",
          "KH",
          "KI",
          "KM",
          "KN",
          "KR",
          "KW",
          "KZ",
          "LA",
          "LB",
          "LC",
          "LI",
          "LK",
          "LR",
          "LS",
          "LT",
          "LU",
          "LV",
          "LY",
          "MA",
          "MC",
          "MD",
          "ME",
          "MG",
          "MH",
          "MK",
          "ML",
          "MN",
          "MO",
          "MR",
          "MT",
          "MU",
          "MV",
          "MW",
          "MX",
          "MY",
          "MZ",
          "NA",
          "NE",
          "NG",
          "NI",
          "NL",
          "NO",
          "NP",
          "NR",
          "NZ",
          "OM",
          "PA",
          "PE",
          "PG",
          "PH",
          "PK",
          "PL",
          "PS",
          "PT",
          "PW",
          "PY",
          "QA",
          "RO",
          "RS",
          "RW",
          "SA",
          "SB",
          "SC",
          "SE",
          "SG",
          "SI",
          "SK",
          "SL",
          "SM",
          "SN",
          "SR",
          "ST",
          "SV",
          "SZ",
          "TD",
          "TG",
          "TH",
          "TJ",
          "TL",
          "TN",
          "TO",
          "TR",
          "TT",
          "TV",
          "TW",
          "TZ",
          "UA",
          "UG",
          "US",
          "UY",
          "UZ",
          "VC",
          "VE",
          "VN",
          "VU",
          "WS",
          "XK",
          "ZA",
          "ZM",
          "ZW"
        ],
        "disc_number": 1,
        "duration_ms": 187828,
        "explicit": false,
        "external_ids": {
          "isrc": "USEAX1602879"
        },
        "external_urls": {
          "spotify": "https://open.spotify.com/track/6ugrRFZUNIpLiqhLUgC7ix"
        },
        "href": "https://api.spotify.com/v1/tracks/6ugrRFZUNIpLiqhLUgC7ix",
        "id": "6ugrRFZUNIpLiqhLUgC7ix",
        "is_local": false,
        "name": "Flowers",
        "popularity": 50,
        "preview_url": "https://p.scdn.co/mp3-preview/3d26f0ac0b832b249103423f5998c18f77a4f259?cid=b5e32fa592ff4292bb18999432fd729a",
        "track_number": 14,
        "type": "track",
        "uri": "spotify:track:6ugrRFZUNIpLiqhLUgC7ix"
      },
      {
        "album": {
          "album_type": "compilation",
          "artists": [
            {
              "external_urls": {
                "spotify": "https://open.spotify.com/artist/0LyfQWJT6nXafLPZqxe9Of"
              },
              "href": "https://api.spotify.com/v1/artists/0LyfQWJT6nXafLPZqxe9Of",
              "id": "0LyfQWJT6nXafLPZqxe9Of",
              "name": "Various Artists",
              "type": "artist",
              "uri": "spotify:artist:0LyfQWJT6nXafLPZqxe9Of"
            }
          ],
          "available_markets": [
            "AE",
            "AL",
            "AR",
            "AT",
            "AU",
            "BA",
            "BE",
            "BG",
            "BH",
            "BO",
            "BR",
            "CA",
            "CH",
            "CI",
            "CL",
            "CM",
            "CO",
            "CR",
            "CW",
            "CY",
            "CZ",
            "DE",
            "DK",
            "DO",
            "DZ",
            "EC",
            "EE",
            "EG",
            "ES",
            "FI",
            "FR",
            "GB",
            "GH",
            "GR",
            "GT",
            "HK",
            "HN",
            "HR",
            "HU",
            "ID",
            "IE",
            "IL",
            "IN",
            "IS",
            "IT",
            "JP",
            "KE",
            "KH",
            "KR",
            "KW",
            "LB",
            "LK",
            "LT",
            "LU",
            "LV",
            "MA",
            "ME",
            "MK",
            "MT",
            "MX",
            "MY",
            "NG",
            "NI",
            "NL",
            "NO",
            "NZ",
            "OM",
            "PA",
            "PE",
            "PH",
            "PL",
            "PT",
            "PY",
            "QA",
            "RO",
            "RS",
            "SA",
            "SE",
            "SG",
            "SI",
            "SK",
            "SN",
            "SV",
            "TH",
            "TN",
            "TR",
            "TT",
            "TW",
            "UA",
            "US",
            "UY",
            "VE",
            "VN",
            "XK",
            "ZA"
          ],
          "external_urls": {
            "spotify": "https://open.spotify.com/album/4j8WQT2cQ86SYtAGgicmBW"
          },
          "href": "https://api.spotify.com/v1/albums/4j8WQT2cQ86SYtAGgicmBW",
          "id": "4j8WQT2cQ86SYtAGgicmBW",
          "images": [
            {
              "height": 640,
              "url": "https://i.scdn.co/image/ab67616d0000b273c377dcae4994b338de60eb6b",
              "width": 640
            },
            {
              "height": 300,
              "url": "https://i.scdn.co/image/ab67616d00001e02c377dcae4994b338de60eb6b",
              "width": 300
            },
            {
              "height": 64,
              "url": "https://i.scdn.co/image/ab67616d00004851c377dcae4994b338de60eb6b",
              "width": 64
            }
          ],
          "name": "New Years Party 2023",
          "release_date": "2022-12-01",
          "release_date_precision": "day",
          "total_tracks": 53,
          "type": "album",
          "uri": "spotify:album:4j8WQT2cQ86SYtAGgicmBW"
        },
        "artists": [
          {
            "external_urls": {
              "spotify": "https://open.spotify.com/artist/22bE4uQ6baNwSHPVcDxLCe"
            },
            "href": "https://api.spotify.com/v1/artists/22bE4uQ6baNwSHPVcDxLCe",
            "id": "22bE4uQ6baNwSHPVcDxLCe",
            "name": "The Rolling Stones",
            "type": "artist",
            "uri": "spotify:artist:22bE4uQ6baNwSHPVcDxLCe"
          }
        ],
        "available_markets": [
          "AE",
          "AL",
          "AR",
          "AT",
          "AU",
          "BA",
          "BE",
          "BG",
          "BH",
          "BO",
          "BR",
          "CA",
          "CH",
          "CI",
          "CL",
          "CM",
          "CO",
          "CR",
          "CW",
          "CY",
          "CZ",
          "DE",
          "DK",
          "DO",
          "DZ",
          "EC",
          "EE",
          "EG",
          "ES",
          "FI",
          "FR",
          "GB",
          "GH",
          "GR",
          "GT",
          "HK",
          "HN",
          "HR",
          "HU",
          "ID",
          "IE",
          "IL",
          "IN",
          "IS",
          "IT",
          "JP",
          "KE",
          "KH",
          "KR",
          "KW",
          "LB",
          "LK",
          "LT",
          "LU",
          "LV",
          "MA",
          "ME",
          "MK",
          "MT",
          "MX",
          "MY",
          "NG",
          "NI",
          "NL",
          "NO",
          "NZ",
          "OM",
          "PA",
          "PE",
          "PH",
          "PL",
          "PT",
          "PY",
          "QA",
          "RO",
          "RS",
          "SA",
          "SE",
          "SG",
          "SI",
          "SK",
          "SN",
          "SV",
          "TH",
          "TN",
          "TR",
          "TT",
          "TW",
          "UA",
          "US",
          "UY",
          "VE",
          "VN",
          "XK",
          "ZA"
        ],
        "disc_number": 1,
        "duration_ms": 244533,
        "explicit": false,
        "external_ids": {
          "isrc": "GBUM70909472"
        },
        "external_urls": {
          "spotify": "https://open.spotify.com/track/7575Qxh9eugizjq6SvP4DK"
        },
        "href": "https://api.spotify.com/v1/tracks/7575Qxh9eugizjq6SvP4DK",
        "id": "7575Qxh9eugizjq6SvP4DK",
        "is_local": false,
        "name": "Dead Flowers - 2009 Mix",
        "popularity": 1,
        "preview_url": "https://p.scdn.co/mp3-preview/377329fd1b40ca1fbeaba5b445b567840dcd354c?cid=b5e32fa592ff4292bb18999432fd729a",
        "track_number": 19,
        "type": "track",
        "uri": "spotify:track:7575Qxh9eugizjq6SvP4DK"
      },
      {
        "album": {
          "album_type": "compilation",
          "artists": [
            {
              "external_urls": {
                "spotify": "https://open.spotify.com/artist/0LyfQWJT6nXafLPZqxe9Of"
              },
              "href": "https://api.spotify.com/v1/artists/0LyfQWJT6nXafLPZqxe9Of",
              "id": "0LyfQWJT6nXafLPZqxe9Of",
              "name": "Various Artists",
              "type": "artist",
              "uri": "spotify:artist:0LyfQWJT6nXafLPZqxe9Of"
            }
          ],
          "available_markets": [
            "AE",
            "AL",
            "AR",
            "AT",
            "AU",
            "BA",
            "BG",
            "BH",
            "BO",
            "BR",
            "CA",
            "CH",
            "CI",
            "CL",
            "CM",
            "CO",
            "CR",
            "CY",
            "CZ",
            "DE",
            "DK",
            "DO",
            "DZ",
            "EC",
            "EE",
            "EG",
            "ES",
            "FI",
            "FR",
            "GB",
            "GH",
            "GR",
            "GT",
            "HK",
            "HN",
            "HR",
            "HU",
            "ID",
            "IE",
            "IL",
            "IN",
            "IS",
            "IT",
            "JP",
            "KE",
            "KH",
            "KR",
            "KW",
            "LB",
            "LK",
            "LT",
            "LV",
            "MA",
            "ME",
            "MK",
            "MT",
            "MX",
            "MY",
            "NG",
            "NI",
            "NZ",
            "OM",
            "PA",
            "PE",
            "PH",
            "PL",
            "PT",
            "PY",
            "QA",
            "RO",
            "RS",
            "SA",
            "SG",
            "SI",
            "SK",
            "SN",
            "SV",
            "TH",
            "TN",
            "TR",
            "TT",
            "TW",
            "UA",
            "US",
            "UY",
            "VE",
            "VN",
            "XK",
            "ZA"
          ],
          "external_urls": {
            "spotify": "https://open.spotify.com/album/6pE3CyFpqsy9acjSd65iyY"
          },
          "href": "https://api.spotify.com/v1/albums/6pE3CyFpqsy9acjSd65iyY",
          "id": "6pE3CyFpqsy9acjSd65iyY",
          "images": [
            {
              "height": 640,
              "url": "https://i.scdn.co/image/ab67616d0000b273ea63d362a63da1479bffeb45",
              "width": 640
            },
            {
              "height": 300,
              "url": "https://i.scdn.co/image/ab67616d00001e02ea63d362a63da1479bffeb45",
              "width": 300
            },
            {
              "height": 64,
              "url": "https://i.scdn.co/image/ab67616d00004851ea63d362a63da1479bffeb45",
              "width": 64
            }
          ],
          "name": "The Best New Years Playlist 2023",
          "release_date": "2022-12-17",
          "release_date_precision": "day",
          "total_tracks": 51,
          "type": "album",
          "uri": "spotify:album:6pE3CyFpqsy9acjSd65iyY"
        },
        "artists": [
          {
            "external_urls": {
              "spotify": "https://open.spotify.com/artist/5TvdGhdmRObqOkU6eGfXb5"
            },
            "href": "https://api.spotify.com/v1/artists/5TvdGhdmRObqOkU6eGfXb5",
            "id": "5TvdGhdmRObqOkU6eGfXb5",
            "name": "Preston Pablo",
            "type": "artist",
            "uri": "spotify:artist:5TvdGhdmRObqOkU6eGfXb5"
          },
          {
            "external_urls": {
              "spotify": "https://open.spotify.com/artist/2uFC1dAj5b0YU7vulKNZ0p"
            },
            "href": "https://api.spotify.com/v1/artists/2uFC1dAj5b0YU7vulKNZ0p",
            "id": "2uFC1dAj5b0YU7vulKNZ0p",
            "name": "Banx & Ranx",
            "type": "artist",
            "uri": "spotify:artist:2uFC1dAj5b0YU7vulKNZ0p"
          }
        ],
        "available_markets": [
          "AE",
          "AL",
          "AR",
          "AT",
          "AU",
          "BA",
          "BG",
          "BH",
          "BO",
          "BR",
          "CA",
          "CH",
          "CI",
          "CL",
          "CM",
          "CO",
          "CR",
          "CY",
          "CZ",
          "DE",
          "DK",
          "DO",
          "DZ",
          "EC",
          "EE",
          "EG",
          "ES",
          "FI",
          "FR",
          "GB",
          "GH",
          "GR",
          "GT",
          "HK",
          "HN",
          "HR",
          "HU",
          "ID",
          "IE",
          "IL",
          "IN",
          "IS",
          "IT",
          "JP",
          "KE",
          "KH",
          "KR",
          "KW",
          "LB",
          "LK",
          "LT",
          "LV",
          "MA",
          "ME",
          "MK",
          "MT",
          "MX",
          "MY",
          "NG",
          "NI",
          "NZ",
          "OM",
          "PA",
          "PE",
          "PH",
          "PL",
          "PT",
          "PY",
          "QA",
          "RO",
          "RS",
          "SA",
          "SG",
          "SI",
          "SK",
          "SN",
          "SV",
          "TH",
          "TN",
          "TR",
          "TT",
          "TW",
          "UA",
          "US",
          "UY",
          "VE",
          "VN",
          "XK",
          "ZA"
        ],
        "disc_number": 1,
        "duration_ms": 168126,
        "explicit": false,
        "external_ids": {
          "isrc": "CAUM72200107"
        },
        "external_urls": {
          "spotify": "https://open.spotify.com/track/0PZscePyWZP73sQx1KA73d"
        },
        "href": "https://api.spotify.com/v1/tracks/0PZscePyWZP73sQx1KA73d",
        "id": "0PZscePyWZP73sQx1KA73d",
        "is_local": false,
        "name": "Flowers Need Rain",
        "popularity": 12,
        "preview_url": "https://p.scdn.co/mp3-preview/8c4d8e172f913ec1df29c0fc2d8c3c7958f0425b?cid=b5e32fa592ff4292bb18999432fd729a",
        "track_number": 26,
        "type": "track",
        "uri": "spotify:track:0PZscePyWZP73sQx1KA73d"
      },
      {
        "album": {
          "album_type": "single",
          "artists": [
            {
              "external_urls": {
                "spotify": "https://open.spotify.com/artist/3uzzXW1FnrjH1Ikic7DLsg"
              },
              "href": "https://api.spotify.com/v1/artists/3uzzXW1FnrjH1Ikic7DLsg",
              "id": "3uzzXW1FnrjH1Ikic7DLsg",
              "name": "Stephen Cuthbert",
              "type": "artist",
              "uri": "spotify:artist:3uzzXW1FnrjH1Ikic7DLsg"
            }
          ],
          "available_markets": [
            "AD",
            "AE",
            "AG",
            "AL",
            "AM",
            "AO",
            "AR",
            "AT",
            "AU",
            "AZ",
            "BA",
            "BB",
            "BD",
            "BE",
            "BF",
            "BG",
            "BH",
            "BI",
            "BJ",
            "BN",
            "BO",
            "BR",
            "BS",
            "BT",
            "BW",
            "BY",
            "BZ",
            "CA",
            "CD",
            "CG",
            "CH",
            "CI",
            "CL",
            "CM",
            "CO",
            "CR",
            "CV",
            "CW",
            "CY",
            "CZ",
            "DE",
            "DJ",
            "DK",
            "DM",
            "DO",
            "DZ",
            "EC",
            "EE",
            "EG",
            "ES",
            "ET",
            "FI",
            "FJ",
            "FM",
            "FR",
            "GA",
            "GB",
            "GD",
            "GE",
            "GH",
            "GM",
            "GN",
            "GQ",
            "GR",
            "GT",
            "GW",
            "GY",
            "HK",
            "HN",
            "HR",
            "HT",
            "HU",
            "ID",
            "IE",
            "IL",
            "IN",
            "IQ",
            "IS",
            "IT",
            "JM",
            "JO",
            "JP",
            "KE",
            "KG",
            "KH",
            "KI",
            "KM",
            "KN",
            "KR",
            "KW",
            "KZ",
            "LA",
            "LB",
            "LC",
            "LI",
            "LK",
            "LR",
            "LS",
            "LT",
            "LU",
            "LV",
            "LY",
            "MA",
            "MC",
            "MD",
            "ME",
            "MG",
            "MH",
            "MK",
            "ML",
            "MN",
            "MO",
            "MR",
            "MT",
            "MU",
            "MV",
            "MW",
            "MX",
            "MY",
            "MZ",
            "NA",
            "NE",
            "NG",
            "NI",
            "NL",
            "NO",
            "NP",
            "NR",
            "NZ",
            "OM",
            "PA",
            "PE",
            "PG",
            "PH",
            "PK",
            "PL",
            "PS",
            "PT",
            "PW",
            "PY",
            "QA",
            "RO",
            "RS",
            "RW",
            "SA",
            "SB",
            "SC",
            "SE",
            "SG",
            "SI",
            "SK",
            "SL",
            "SM",
            "SN",
            "SR",
            "ST",
            "SV",
            "SZ",
            "TD",
            "TG",
            "TH",
            "TJ",
            "TL",
            "TN",
            "TO",
            "TR",
            "TT",
            "TV",
            "TW",
            "TZ",
            "UA",
            "UG",
            "US",
            "UY",
            "UZ",
            "VC",
            "VE",
            "VN",
            "VU",
            "WS",
            "XK",
            "ZA",
            "ZM",
            "ZW"
          ],
          "external_urls": {
            "spotify": "https://open.spotify.com/album/2gqlbjPkHsQJYRaiz38gsY"
          },
          "href": "https://api.spotify.com/v1/albums/2gqlbjPkHsQJYRaiz38gsY",
          "id": "2gqlbjPkHsQJYRaiz38gsY",
          "images": [
            {
              "height": 640,
              "url": "https://i.scdn.co/image/ab67616d0000b2738c49e53a0e429bf2ab404cad",
              "width": 640
            },
            {
              "height": 300,
              "url": "https://i.scdn.co/image/ab67616d00001e028c49e53a0e429bf2ab404cad",
              "width": 300
            },
            {
              "height": 64,
              "url": "https://i.scdn.co/image/ab67616d000048518c49e53a0e429bf2ab404cad",
              "width": 64
            }
          ],
          "name": "Flowers",
          "release_date": "2023-01-27",
          "release_date_precision": "day",
          "total_tracks": 1,
          "type": "album",
          "uri": "spotify:album:2gqlbjPkHsQJYRaiz38gsY"
        },
        "artists": [
          {
            "external_urls": {
              "spotify": "https://open.spotify.com/artist/3uzzXW1FnrjH1Ikic7DLsg"
            },
            "href": "https://api.spotify.com/v1/artists/3uzzXW1FnrjH1Ikic7DLsg",
            "id": "3uzzXW1FnrjH1Ikic7DLsg",
            "name": "Stephen Cuthbert",
            "type": "artist",
            "uri": "spotify:artist:3uzzXW1FnrjH1Ikic7DLsg"
          }
        ],
        "available_markets": [
          "AD",
          "AE",
          "AG",
          "AL",
          "AM",
          "AO",
          "AR",
          "AT",
          "AU",
          "AZ",
          "BA",
          "BB",
          "BD",
          "BE",
          "BF",
          "BG",
          "BH",
          "BI",
          "BJ",
          "BN",
          "BO",
          "BR",
          "BS",
          "BT",
          "BW",
          "BY",
          "BZ",
          "CA",
          "CD",
          "CG",
          "CH",
          "CI",
          "CL",
          "CM",
          "CO",
          "CR",
          "CV",
          "CW",
          "CY",
          "CZ",
          "DE",
          "DJ",
          "DK",
          "DM",
          "DO",
          "DZ",
          "EC",
          "EE",
          "EG",
          "ES",
          "ET",
          "FI",
          "FJ",
          "FM",
          "FR",
          "GA",
          "GB",
          "GD",
          "GE",
          "GH",
          "GM",
          "GN",
          "GQ",
          "GR",
          "GT",
          "GW",
          "GY",
          "HK",
          "HN",
          "HR",
          "HT",
          "HU",
          "ID",
          "IE",
          "IL",
          "IN",
          "IQ",
          "IS",
          "IT",
          "JM",
          "JO",
          "JP",
          "KE",
          "KG",
          "KH",
          "KI",
          "KM",
          "KN",
          "KR",
          "KW",
          "KZ",
          "LA",
          "LB",
          "LC",
          "LI",
          "LK",
          "LR",
          "LS",
          "LT",
          "LU",
          "LV",
          "LY",
          "MA",
          "MC",
          "MD",
          "ME",
          "MG",
          "MH",
          "MK",
          "ML",
          "MN",
          "MO",
          "MR",
          "MT",
          "MU",
          "MV",
          "MW",
          "MX",
          "MY",
          "MZ",
          "NA",
          "NE",
          "NG",
          "NI",
          "NL",
          "NO",
          "NP",
          "NR",
          "NZ",
          "OM",
          "PA",
          "PE",
          "PG",
          "PH",
          "PK",
          "PL",
          "PS",
          "PT",
          "PW",
          "PY",
          "QA",
          "RO",
          "RS",
          "RW",
          "SA",
          "SB",
          "SC",
          "SE",
          "SG",
          "SI",
          "SK",
          "SL",
          "SM",
          "SN",
          "SR",
          "ST",
          "SV",
          "SZ",
          "TD",
          "TG",
          "TH",
          "TJ",
          "TL",
          "TN",
          "TO",
          "TR",
          "TT",
          "TV",
          "TW",
          "TZ",
          "UA",
          "UG",
          "US",
          "UY",
          "UZ",
          "VC",
          "VE",
          "VN",
          "VU",
          "WS",
          "XK",
          "ZA",
          "ZM",
          "ZW"
        ],
        "disc_number": 1,
        "duration_ms": 199145,
        "explicit": false,
        "external_ids": {
          "isrc": "QZFZ62311828"
        },
        "external_urls": {
          "spotify": "https://open.spotify.com/track/2QLfv4iT843NGKw8OzCuXR"
        },
        "href": "https://api.spotify.com/v1/tracks/2QLfv4iT843NGKw8OzCuXR",
        "id": "2QLfv4iT843NGKw8OzCuXR",
        "is_local": false,
        "name": "Flowers",
        "popularity": 30,
        "preview_url": "https://p.scdn.co/mp3-preview/70e4bea33e5f89f7871cc22a7a55808d9bbfed08?cid=b5e32fa592ff4292bb18999432fd729a",
        "track_number": 1,
        "type": "track",
        "uri": "spotify:track:2QLfv4iT843NGKw8OzCuXR"
      }
    ],
    "limit": 10,
    "next": "https://api.spotify.com/v1/search?query=Flowers%2C+year%3D2023&type=track&offset=10&limit=10",
    "offset": 0,
    "previous": null,
    "total": 1000
  }
}